Metadata-Version: 1.1
Name: 15five-django-ajax-selects
Version: 1.5.2.155
Summary: Edit ForeignKey, ManyToManyField and CharField in Django Admin using jQuery UI AutoComplete.
Home-page: https://github.com/crucialfelix/django-ajax-selects/
Author: Chris Sattinger
Author-email: crucialfelix@gmail.com
License: MIT
Platform: UNKNOWN
Classifier: Programming Language :: Python
Classifier: Programming Language :: Python :: 2
Classifier: Programming Language :: Python :: 3
Classifier: Development Status :: 5 - Production/Stable
Classifier: Environment :: Web Environment
Classifier: Intended Audience :: Developers
Classifier: License :: OSI Approved :: MIT License
Classifier: Operating System :: OS Independent
Classifier: Topic :: Software Development :: Libraries :: Python Modules
Classifier: Topic :: Software Development :: User Interfaces
Classifier: Framework :: Django
